microstack/__init__.py
microstack/agents/__init__.py
microstack/agents/microscopy_router.py
microstack/agents/session_manager.py
microstack/agents/state.py
microstack/agents/structure_generator.py
microstack/agents/structure_validator.py
microstack/agents/workflow.py
microstack/agents/microscopy/__init__.py
microstack/agents/microscopy/afm.py
microstack/agents/microscopy/iets.py
microstack/agents/microscopy/stm.py
microstack/agents/microscopy/tem.py
microstack/cli/__init__.py
microstack/cli/app.py
microstack/cli/interactive.py
microstack/io/__init__.py
microstack/io/nsid.py
microstack/llm/__init__.py
microstack/llm/anthropic.py
microstack/llm/client.py
microstack/llm/deepseek.py
microstack/llm/gemini.py
microstack/llm/models.py
microstack/llm/prompts.py
microstack/relaxation/__init__.py
microstack/relaxation/comparison.py
microstack/relaxation/generate_surfaces.py
microstack/relaxation/materials_project.py
microstack/relaxation/relax_report_generator.py
microstack/relaxation/scilink_integration.py
microstack/relaxation/surface_relaxation.py
microstack/utils/__init__.py
microstack/utils/config.py
microstack/utils/exceptions.py
microstack/utils/gpu_detection.py
microstack/utils/logging.py
microstack/utils/report_generator.py
microstack/utils/settings.py
microstack/web/__init__.py
microstack/web/api.py
microstack-0.1.0.dist-info/licenses/LICENSE
microstack-0.1.0.dist-info/METADATA
microstack-0.1.0.dist-info/WHEEL
microstack-0.1.0.dist-info/entry_points.txt
microstack-0.1.0.dist-info/top_level.txt
microstack-0.1.0.dist-info/RECORD
