Metadata-Version: 2.4
Name: microstack
Version: 0.1.0
Summary: AI Materials Scientist - Analyze atomic surfaces using MLIPs and various microscopy simulation techniques.
Author: Team µStack
Author-email: Aritra Roy <contact@aritraroy.live>, Kevin Shen <kevin.shen@noble.ai>, Ben Blaiszik <blaiszik@uchicago.edu>, Piyush Ranjan Maharana <piyushmaharana15@gmail.com>
Keywords: materials science,machine learning,surface science,MACE,atomic simulation
Classifier: Development Status :: 3 - Alpha
Classifier: Intended Audience :: Science/Research
Classifier: Topic :: Scientific/Engineering :: Chemistry
Classifier: Topic :: Scientific/Engineering :: Physics
Classifier: License :: OSI Approved :: MIT License
Classifier: Programming Language :: Python :: 3
Classifier: Programming Language :: Python :: 3.12
Classifier: Programming Language :: Python :: 3.13
Requires-Python: >=3.12
License-File: LICENSE
Requires-Dist: ase>=3.26
Requires-Dist: mace-torch>=0.3.12
Requires-Dist: torch>=2.0.0
Requires-Dist: torch-sim-atomistic>=0.3.0
Requires-Dist: cuequivariance-torch
Requires-Dist: scilink
Requires-Dist: gpaw
Requires-Dist: ppafm[opencl]
Requires-Dist: sidpy
Requires-Dist: pyNSID
Requires-Dist: h5py
Requires-Dist: google-generativeai>=0.8.0
Requires-Dist: anthropic>=0.40.0
Requires-Dist: mp-api>=0.41.0
Requires-Dist: numpy
Requires-Dist: matplotlib
Requires-Dist: langgraph
Requires-Dist: langchain-core
Requires-Dist: langchain-deepseek
Requires-Dist: click
Requires-Dist: rich
Requires-Dist: pydantic
Requires-Dist: pydantic-settings
Requires-Dist: tenacity
Requires-Dist: python-dotenv
Requires-Dist: fastapi
Requires-Dist: uvicorn[standard]
Requires-Dist: websockets
Dynamic: license-file
